src/ALU.sv
module ALU (
    input logic [31:0] A,
    input logic [31:0] B,
    input logic [3:0] ALUOp,
    output logic [31:0] ALURes
);

    always @(*) begin
        case (ALUOp)
            4'b0111: ALURes = A & B; // AND
            4'b0110: ALURes = A | B; // OR
            4'b0000: ALURes = A + B; // ADD
            4'b1000: ALURes = A - B; // SUB
            4'b0010: ALURes = ($signed(A) < $signed(B)) ? 32'b1 : 32'b0; // SLT con signo
            4'b0011: ALURes = (A < B) ? 32'b1 : 32'b0; // SLT sin signo
            4'b0001: ALURes = A << B[4:0]; // SLL
            4'b0101: ALURes = A >> B[4:0]; // SRL
            4'b1101: ALURes = $signed(A) >>> B[4:0]; //SRA
            4'b0100: ALURes = A ^ B; // XOR
        endcase
    end    
endmodule

tb/ALU_tb.sv
`timescale 1ns/1ps

module ALU_tb;
  // Cables de conexion con el modulo
  logic signed [31:0] Atb, Btb;
  logic [3:0]  ALUOptb;
  logic signed [31:0] ALURestb;

  // Instancia de la ALU y pineado
  ALU alu_instance (
    .A(Atb),
    .B(Btb),
    .ALUOp(ALUOptb),
    .ALURes(ALURestb)
  );

  initial begin
    $dumpfile("sim/ALU_tb.vcd");
    $dumpvars(0, ALU_tb);

    // Pruebas básicas
    Atb = 0;  Btb = 0;  ALUOptb = 4'b0000; #10; // ADD: 0 + 0
    Atb = 3;  Btb = 5;  ALUOptb = 4'b0000; #10; // ADD: 3 + 5 = 8
    Atb = 3;  Btb = 5;  ALUOptb = 4'b1000; #10; // SUB: 3 - 5 = -2
    Atb = 1;  Btb = 2;  ALUOptb = 4'b0001; #10; // SLL: 1 << 2 = 4
    Atb = -2; Btb = 3;  ALUOptb = 4'b0010; #10; // SLT: -2 < 3 = 1
    Atb = 2;  Btb = 3;  ALUOptb = 4'b0010; #10; // SLTU: 2 < 3 = 1
    Atb = 4;  Btb = 1;  ALUOptb = 4'b0101; #10; // SRL: 4 >> 1 = 2
    Atb = -8; Btb = 2;  ALUOptb = 4'b1101; #10; // SRA: -8 >>> 2 = -2
    Atb = 3;  Btb = 6;  ALUOptb = 4'b0100; #10; // XOR: 3 ^ 6 = 5
    Atb = 3;  Btb = 6;  ALUOptb = 4'b0110; #10; // OR:  3 | 6 = 7
    Atb = 3;  Btb = 6;  ALUOptb = 4'b0111; #10; // AND: 3 & 6 = 2
    $finish;

  end
endmodule

sim/ALU_tb.vcd
$date
	Sun Nov 02 16:16:05 2025
$end
$version
	Icarus Verilog
$end
$timescale
	1ps
$end
$scope module ALU_tb $end
$var wire 32 ! ALURestb [31:0] $end
$var reg 4 " ALUOptb [3:0] $end
$var reg 32 # Atb [31:0] $end
$var reg 32 $ Btb [31:0] $end
$scope module alu_instance $end
$var wire 32 % A [31:0] $end
$var wire 4 & ALUOp [3:0] $end
$var wire 32 ' B [31:0] $end
$var reg 32 ( ALURes [31:0] $end
$upscope $end
$upscope $end
$enddefinitions $end
$comment Show the parameter values. $end
$dumpall
$end
#0
$dumpvars
b0 (
b0 '
b0 &
b0 %
b0 $
b0 #
b0 "
b0 !
$end
#10000
b1000 !
b1000 (
b101 $
b101 '
b11 #
b11 %
#20000
b11111111111111111111111111111110 !
b11111111111111111111111111111110 (
b1000 "
b1000 &
#30000
b100 !
b100 (
b1 "
b1 &
b10 $
b10 '
b1 #
b1 %
#40000
b1 !
b1 (
b10 "
b10 &
b11 $
b11 '
b11111111111111111111111111111110 #
b11111111111111111111111111111110 %
#50000
b10 #
b10 %
#60000
b10 !
b10 (
b101 "
b101 &
b1 $
b1 '
b100 #
b100 %
#70000
b11111111111111111111111111111110 !
b11111111111111111111111111111110 (
b1101 "
b1101 &
b10 $
b10 '
b11111111111111111111111111111000 #
b11111111111111111111111111111000 %
#80000
b101 !
b101 (
b100 "
b100 &
b110 $
b110 '
b11 #
b11 %
#90000
b111 !
b111 (
b110 "
b110 &
#100000
b10 !
b10 (
b111 "
b111 &
