src/Control_unit.sv
module ControlUnit (
    input  logic [6:0] OpCode,   // [6:0]
    input  logic [2:0] Funct3,   // [14:12]
    input  logic [6:0] Funct7,   // [31:25]
    output logic [4:0] BrOp,
    output logic [3:0] ALUOp,    // código de operación para ALU
    output logic [2:0] DMCtrl,
    output logic [2:0] ImmSrc,
    output logic [1:0] RUDataWrSrc,
    output logic ALUASrc,
    output logic ALUBSrc,
    output logic DMWr,
    output logic RUWr
);

    always @(*) begin
        
        // --- Valores por defecto ---
        BrOp        = 5'b00000;
        ALUOp       = 4'b0000; // ADD por defecto
        DMCtrl      = 3'b000;
        ImmSrc      = 3'b000;
        RUDataWrSrc = 2'b00;
        ALUASrc     = 0;
        ALUBSrc     = 0;
        DMWr        = 0;
        RUWr        = 0;

        case (OpCode)
            // Instrucciones tipo R
            7'b0110011: begin
                RUWr = 1;
                ALUASrc = 0;
                ALUBSrc = 0;

                case (Funct3)
                    3'b000: ALUOp = (Funct7[5]) ? 4'b1000 : 4'b0000; // SUB / ADD
                    3'b111: ALUOp = 4'b0111; // AND
                    3'b110: ALUOp = 4'b0110; // OR
                    3'b100: ALUOp = 4'b0100; // XOR
                    3'b010: ALUOp = 4'b0010; // SLT
                    3'b001: ALUOp = 4'b0001; // SLL
                    3'b101: ALUOp = (Funct7[5]) ? 4'b1101 : 4'b0101; // SRA / SRL
                    default: ALUOp = 4'b0000;
                endcase
            end

            // Instrucciones tipo I
            7'b0010011: begin
                RUWr = 1;
                ALUBSrc = 1;
                ImmSrc = 3'b000;

                case (Funct3)
                    3'b000: ALUOp = 4'b0000; // ADDI
                    3'b111: ALUOp = 4'b0111; // ANDI
                    3'b110: ALUOp = 4'b0110; // ORI
                    3'b100: ALUOp = 4'b0100; // XORI
                    3'b010: ALUOp = 4'b0010; // SLTI
                    3'b001: ALUOp = 4'b0001; // SLLI
                    3'b101: ALUOp = (Funct7[5]) ? 4'b1101 : 4'b0101; // SRAI / SRLI
                    default: ALUOp = 4'b0000;
                endcase
            end

            // Tipo L
            7'b0000011: begin
                RUWr = 1;
                ALUBSrc = 1;
                ALUOp = 4'b0000; // dirección = rs1 + imm
                DMCtrl = Funct3;
                RUDataWrSrc = 2'b10; // dato viene de Data Memory
            end

            // Tipo S
            7'b0100011: begin
                ALUBSrc = 1;
                ALUOp = 4'b0000; // dirección = rs1 + imm
                DMCtrl = Funct3;
                DMWr = 1;
            end

            // Tipo B
            7'b1100011: begin
                ALUOp = 4'b1000; // resta para comparación
                BrOp  = {2'b01, Funct3};
            end

            // Tipo U
            7'b0110111: begin // LUI
                RUWr = 1;
                ALUASrc = 0;
                ALUBSrc = 1;
                ImmSrc = 3'b011; // tipo U
                ALUOp = 4'b0000; // pasa el inmediato (ADD)
                RUDataWrSrc = 2'b00;
            end

            // Tipo U
            7'b0010111: begin // AUIPC
                RUWr = 1;
                ALUASrc = 1;
                ALUBSrc = 1;
                ImmSrc = 3'b011;
                ALUOp = 4'b0000; // ADD
                RUDataWrSrc = 2'b00;
            end


            // Tipo J
            7'b1101111: begin // JAL
                RUWr = 1;
                ALUASrc = 1;
                ALUBSrc = 1;
                ImmSrc = 3'b100; // tipo J
                ALUOp = 4'b0000;
                RUDataWrSrc = 2'b10; // PC + 4
                BrOp = 5'b10000;     // salto incondicional
            end

            // Tipo J
            7'b1100111: begin // JALR
                RUWr = 1;
                ALUASrc = 0;
                ALUBSrc = 1;
                ImmSrc = 3'b000; // tipo I
                ALUOp = 4'b0000;
                RUDataWrSrc = 2'b10;
                BrOp = 5'b10001;
            end

            default: begin
                // sin operación
            end
        endcase
    end
endmodule

tb/Control_unit_tb.sv
module ControlUnit_tb;

    // Entradas
    logic [6:0] OpCode;
    logic [2:0] Funct3;
    logic [6:0] Funct7;

    // Salidas
    logic [4:0] BrOp;
    logic [3:0] ALUOp;
    logic [2:0] DMCtrl;
    logic [2:0] ImmSrc;
    logic [1:0] RUDataWrSrc;
    logic ALUASrc;
    logic ALUBSrc;
    logic DMWr;
    logic RUWr;

    // Instancia del módulo
    ControlUnit CUInstance(
        .OpCode(OpCode),
        .Funct3(Funct3),
        .Funct7(Funct7),
        .BrOp(BrOp),
        .ALUOp(ALUOp),
        .DMCtrl(DMCtrl),
        .ImmSrc(ImmSrc),
        .RUDataWrSrc(RUDataWrSrc),
        .ALUASrc(ALUASrc),
        .ALUBSrc(ALUBSrc),
        .DMWr(DMWr),
        .RUWr(RUWr)
    );

    // Para simular
    initial begin
        $dumpfile("sim/ControlUnit_tb.vcd");
        $dumpvars(0, ControlUnit_tb);

        // ========================
        // INSTRUCCIONES TIPO R
        // ========================
        
        // ADD
        OpCode = 7'b0110011; Funct3 = 3'b000; Funct7 = 7'b0000000; #10;

        // SUB
        Funct7 = 7'b0100000; #10;

        // AND
        Funct3 = 3'b111; Funct7 = 7'b0000000; #10;

        // OR
        Funct3 = 3'b110; #10;


        // ========================
        // TIPO I (ADDI, ANDI, ORI...)
        // ========================

        OpCode = 7'b0010011; Funct3 = 3'b000; Funct7 = 7'b0000000; #10;

        Funct3 = 3'b111; #10; // ANDI

        Funct3 = 3'b110; #10; // ORI


        // ========================
        // TIPO LOAD (LW, LH, LB)
        // ========================

        OpCode = 7'b0000011; Funct3 = 3'b010; #10;

        // ========================
        // TIPO STORE (SW)
        // ========================

        OpCode = 7'b0100011; Funct3 = 3'b010; #10;

        // ========================
        // TIPO B (BEQ, BNE, BLT...)
        // ========================

        OpCode = 7'b1100011; Funct3 = 3'b000; #10; // BEQ

        Funct3 = 3'b001; #10; // BNE

        // ========================
        // TIPO U (LUI)
        // ========================

        OpCode = 7'b0110111; Funct3 = 3'b000; #10;

        // ========================
        // TIPO U (AUIPC)
        // ========================

        OpCode = 7'b0010111; #10;

        // ========================
        // TIPO J (JAL)
        // ========================

        OpCode = 7'b1101111; #10;

        // ========================
        // TIPO J (JALR)
        // ========================

        OpCode = 7'b1100111; Funct3 = 3'b000; #10;
        
        $finish;
    end

endmodule

sim/ControlUnit_tb.vcd
$date
	Thu Nov 13 21:30:16 2025
$end
$version
	Icarus Verilog
$end
$timescale
	1s
$end
$scope module ControlUnit_tb $end
$var wire 1 ! RUWr $end
$var wire 2 " RUDataWrSrc [1:0] $end
$var wire 3 # ImmSrc [2:0] $end
$var wire 1 $ DMWr $end
$var wire 3 % DMCtrl [2:0] $end
$var wire 5 & BrOp [4:0] $end
$var wire 4 ' ALUOp [3:0] $end
$var wire 1 ( ALUBSrc $end
$var wire 1 ) ALUASrc $end
$var reg 3 * Funct3 [2:0] $end
$var reg 7 + Funct7 [6:0] $end
$var reg 7 , OpCode [6:0] $end
$scope module CUInstance $end
$var wire 3 - Funct3 [2:0] $end
$var wire 7 . Funct7 [6:0] $end
$var wire 7 / OpCode [6:0] $end
$var reg 1 ) ALUASrc $end
$var reg 1 ( ALUBSrc $end
$var reg 4 0 ALUOp [3:0] $end
$var reg 5 1 BrOp [4:0] $end
$var reg 3 2 DMCtrl [2:0] $end
$var reg 1 $ DMWr $end
$var reg 3 3 ImmSrc [2:0] $end
$var reg 2 4 RUDataWrSrc [1:0] $end
$var reg 1 ! RUWr $end
$upscope $end
$upscope $end
$enddefinitions $end
$comment Show the parameter values. $end
$dumpall
$end
#0
$dumpvars
b0 4
b0 3
b0 2
b0 1
b0 0
b110011 /
b0 .
b0 -
b110011 ,
b0 +
b0 *
0)
0(
b0 '
b0 &
b0 %
0$
b0 #
b0 "
1!
$end
#10
b1000 '
b1000 0
1!
b100000 +
b100000 .
#20
1!
b111 '
b111 0
b0 +
b0 .
b111 *
b111 -
#30
1!
b110 '
b110 0
b110 *
b110 -
#40
1(
1!
b0 '
b0 0
b0 *
b0 -
b10011 ,
b10011 /
#50
b111 '
b111 0
1!
1(
b111 *
b111 -
#60
1!
1(
b110 '
b110 0
b110 *
b110 -
#70
b10 "
b10 4
b10 %
b10 2
1!
1(
b0 '
b0 0
b10 *
b10 -
b11 ,
b11 /
#80
1$
0!
1(
b0 "
b0 4
b10 %
b10 2
b100011 ,
b100011 /
#90
b1000 &
b1000 1
b1000 '
b1000 0
0$
0(
b0 %
b0 2
b0 *
b0 -
b1100011 ,
b1100011 /
#100
b1000 '
b1000 0
b1001 &
b1001 1
b1 *
b1 -
#110
b11 #
b11 3
1(
1!
b0 '
b0 0
b0 &
b0 1
b0 *
b0 -
b110111 ,
b110111 /
#120
1)
1!
1(
b11 #
b11 3
b10111 ,
b10111 /
#130
b10000 &
b10000 1
b10 "
b10 4
1!
1(
1)
b100 #
b100 3
b1101111 ,
b1101111 /
#140
1!
1(
0)
b10 "
b10 4
b0 #
b0 3
b10001 &
b10001 1
b1100111 ,
b1100111 /
