src/Data_memory.sv
module DataMemory (
    input  logic [31:0] Address,    // dirección calculada por la ALU
    input  logic [31:0] DataWr,     // dato a escribir (desde rs2)
    input  logic DMWr,              // 1 = escribir, 0 = leer
    input  logic [2:0]  DMCtrl,     // controla tipo de acceso (byte, half, word)
    output logic [31:0] DataRd      // dato leído
);

    // Memoria de datos (256 palabras = 1 KB)
    logic [31:0] mem [0:255];

    // Escritura combinacional
    always @(*) begin
        if (DMWr) begin
            case (DMCtrl)
                3'b000: mem[Address[9:2]][(Address[1:0]*8) +: 8]  = DataWr[7:0];    // SB
                3'b001: mem[Address[9:2]][(Address[1]*16) +: 16]  = DataWr[15:0];   // SH
                3'b010: mem[Address[9:2]]                          = DataWr;        // SW
                default: ;
            endcase
        end
    end

    // Lectura combinacional
    always @(*) begin
        case (DMCtrl)
            3'b000: DataRd = {{24{mem[Address[9:2]][(Address[1:0]*8)+7]}},
                               mem[Address[9:2]][(Address[1:0]*8) +: 8]};       // LB
            3'b001: DataRd = {{16{mem[Address[9:2]][(Address[1]*16)+15]}},
                               mem[Address[9:2]][(Address[1]*16) +: 16]};       // LH
            3'b010: DataRd = mem[Address[9:2]];                                 // LW
            3'b100: DataRd = {24'b0, mem[Address[9:2]][(Address[1:0]*8) +: 8]}; // LBU
            3'b101: DataRd = {16'b0, mem[Address[9:2]][(Address[1]*16) +: 16]}; // LHU
            default: DataRd = 32'b0;
        endcase
    end

endmodule

tb/Data_memory_tb.sv
`timescale 1ns/1ps

module DataMemory_tb;

  // Señales de conexión
  logic [31:0] Address_tb;
  logic [31:0] DataWr_tb;
  logic        DMWr_tb;       
  logic [2:0]  DMCtrl_tb;     
  logic [31:0] DataRd_tb;

  // Instancia del módulo
  DataMemory DM_instance (
    .Address(Address_tb),
    .DataWr(DataWr_tb),
    .DMWr(DMWr_tb),
    .DMCtrl(DMCtrl_tb),
    .DataRd(DataRd_tb)
  );

  initial begin
    $dumpfile("sim/Data_memory_tb.vcd");
    $dumpvars(0, DataMemory_tb);

    // Inicialización
    Address_tb = 0;
    DataWr_tb  = 0;
    DMWr_tb    = 0;
    DMCtrl_tb  = 3'b000;

    // =====================================================
    // PRUEBA 1 — SW: escribir palabra completa
    // =====================================================
    Address_tb = 32'h00000000;
    DataWr_tb  = 32'hAABBCCDD;
    DMWr_tb    = 1;
    DMCtrl_tb  = 3'b010;   // SW
    #10;

    // Leer la palabra
    DMWr_tb    = 0;
    #10;

    // =====================================================
    // PRUEBA 2 — SB: escribir byte bajo
    // =====================================================
    Address_tb = 32'h00000004;   // dirección siguiente
    DataWr_tb  = 32'h000000EE;
    DMWr_tb    = 1;
    DMCtrl_tb  = 3'b000;   // SB
    #10;

    // Leer byte (LB)
    DMWr_tb    = 0;
    DMCtrl_tb  = 3'b000;   // LB
    #10;

    // Leer byte sin signo (LBU)
    DMCtrl_tb  = 3'b100;   // LBU
    #10;

    // =====================================================
    // PRUEBA 3 — SH: escribir HALFWORD
    // =====================================================
    Address_tb = 32'h00000008;
    DataWr_tb  = 32'h0000FACE;
    DMCtrl_tb  = 3'b001;   // SH
    DMWr_tb    = 1;
    #10;

    // Leer HALFWORD (LH)
    DMWr_tb    = 0;
    DMCtrl_tb  = 3'b001;   // LH
    #10;

    // Leer HALFWORD sin signo (LHU)
    DMCtrl_tb  = 3'b101;   // LHU
    #10;

    // =====================================================
    // PRUEBA 4 — LW: verificar lectura de palabra completa
    // =====================================================
    Address_tb = 32'h00000000;
    DMCtrl_tb  = 3'b010;  // LW
    #10;

    // Fin de simulación
    $finish;
  end

endmodule

sim/Data_memory_tb.vcd
$date
	Fri Nov 14 14:55:39 2025
$end
$version
	Icarus Verilog
$end
$timescale
	1ps
$end
$scope module DataMemory_tb $end
$var wire 32 ! DataRd_tb [31:0] $end
$var reg 32 " Address_tb [31:0] $end
$var reg 3 # DMCtrl_tb [2:0] $end
$var reg 1 $ DMWr_tb $end
$var reg 32 % DataWr_tb [31:0] $end
$scope module DM_instance $end
$var wire 32 & Address [31:0] $end
$var wire 3 ' DMCtrl [2:0] $end
$var wire 1 $ DMWr $end
$var wire 32 ( DataWr [31:0] $end
$var reg 32 ) DataRd [31:0] $end
$upscope $end
$upscope $end
$enddefinitions $end
$comment Show the parameter values. $end
$dumpall
$end
#0
$dumpvars
b10101010101110111100110011011101 )
b10101010101110111100110011011101 (
b10 '
b0 &
b10101010101110111100110011011101 %
1$
b10 #
b0 "
b10101010101110111100110011011101 !
$end
#10000
0$
#20000
b11111111111111111111111111101110 !
b11111111111111111111111111101110 )
b0 #
b0 '
1$
b11101110 %
b11101110 (
b100 "
b100 &
#30000
0$
#40000
b11101110 !
b11101110 )
b100 #
b100 '
#50000
b11111111111111111111101011001110 !
b11111111111111111111101011001110 )
1$
b1 #
b1 '
b1111101011001110 %
b1111101011001110 (
b1000 "
b1000 &
#60000
0$
#70000
b1111101011001110 !
b1111101011001110 )
b101 #
b101 '
#80000
b10101010101110111100110011011101 !
b10101010101110111100110011011101 )
b10 #
b10 '
b0 "
b0 &
