src/Program_counter.sv
module ProgramCounter(
    input logic clk,            // Señal de reloj
    input logic reset,          // Señal de reset
    input logic [31:0] PcNext,  // Proxima direccion de memoria
    output logic [31:0] Pc      // Direccion de memoria actual
);

    always_ff @(posedge clk or posedge reset) begin
        if (reset)
            Pc <= 32'b0;
        else
            Pc <= PcNext;
    end
endmodule

tb/PC_tb.sv
`timescale 1ns/1ps

module ProgramCounter_tb;

  // Señales del TB
  logic clk;
  logic reset;
  logic [31:0] PcNext;
  logic [31:0] Pc;

  // Instancia del módulo
  ProgramCounter pc_instance (
    .clk(clk),
    .reset(reset),
    .PcNext(PcNext),
    .Pc(Pc)
  );

  // Generación del reloj (10 ns)
  always #5 clk = ~clk;

  initial begin
    $dumpfile("sim/PC_tb.vcd");
    $dumpvars(0, ProgramCounter_tb);

    // Inicialización
    clk = 0;
    reset = 0;
    PcNext = 0;

    // --- Prueba de reset ---
    reset = 1; #10;
    reset = 0; #10;

    // --- Prueba de avance ---
    PcNext = 32'h00000004; #10;  // PC = 4
    PcNext = 32'h00000008; #10;  // PC = 8
    PcNext = 32'h0000000C; #10;  // PC = 12

    // --- Reset final ---
    reset = 1; #10;
    reset = 0; #10;

    $finish;
  end

endmodule

sim/PC_tb.vcd
$date
	Thu Nov 13 21:57:25 2025
$end
$version
	Icarus Verilog
$end
$timescale
	1ps
$end
$scope module ProgramCounter_tb $end
$var wire 32 ! Pc [31:0] $end
$var reg 32 " PcNext [31:0] $end
$var reg 1 # clk $end
$var reg 1 $ reset $end
$scope module pc_instance $end
$var wire 32 % PcNext [31:0] $end
$var wire 1 # clk $end
$var wire 1 $ reset $end
$var reg 32 & Pc [31:0] $end
$upscope $end
$upscope $end
$enddefinitions $end
$comment Show the parameter values. $end
$dumpall
$end
#0
$dumpvars
b0 &
b0 %
1$
0#
b0 "
b0 !
$end
#5000
1#
#10000
0#
0$
#15000
1#
#20000
0#
b100 "
b100 %
#25000
b100 !
b100 &
1#
#30000
0#
b1000 "
b1000 %
#35000
b1000 !
b1000 &
1#
#40000
0#
b1100 "
b1100 %
#45000
b1100 !
b1100 &
1#
#50000
b0 !
b0 &
0#
1$
#55000
1#
#60000
0#
0$
#65000
b1100 !
b1100 &
1#
